Metadata-Version: 2.1
Name: testgithubactionscookiecuttercppproject
Version: 0.0.0.1
Summary: UNKNOWN
Home-page: UNKNOWN
License: UNKNOWN
Platform: UNKNOWN
